[
  {
    "id": "s001",
    "fileName": "✽0105.00 सामायिक पाठ भाषा (काल अनंत..) Jain Sangrah 9.40.mp3",
    "displayName": "सामायिक पाठ भाषा — काल अनंत (Jain Sangrah)",
    "alternateNames": ["samaik", "samayik", "सामायिक", "काल अनंत", "jain sangrah", "path"],
    "filePath": "media/✽0105.00 सामायिक पाठ भाषा (काल अनंत..) Jain Sangrah 9.40.mp3"
  },
  {
    "id": "s002",
    "fileName": "✽0105.01 सामायिक पाठ भाषा (काल अनंत..) (M) Sup smallsize.mp3",
    "displayName": "सामायिक पाठ भाषा — काल अनंत (M)",
    "alternateNames": ["samaik", "samayik", "सामायिक", "काल अनंत", "small", "mobile"],
    "filePath": "media/✽0105.01 सामायिक पाठ भाषा (काल अनंत..) (M) Sup smallsize.mp3"
  },
  {
    "id": "s003",
    "fileName": "✽0105.04 सामायिक पाठ भाषा (काल अनंत..) New Nocmt 16.56.mp3",
    "displayName": "सामायिक पाठ भाषा — काल अनंत (New)",
    "alternateNames": ["samaik", "samayik", "सामायिक", "काल अनंत", "new", "nocmt"],
    "filePath": "media/✽0105.04 सामायिक पाठ भाषा (काल अनंत..) New Nocmt 16.56.mp3"
  },
  {
    "id": "s004",
    "fileName": "✽104.01 Samaik Path सामायीक प्रतिज्ञा चारो दिशा में Namostu corus.mp3",
    "displayName": "सामायीक प्रतिज्ञा — चारो दिशा में (Namostu)",
    "alternateNames": ["samaik path", "samayik", "प्रतिज्ञा", "namostu", "chorus", "चारो दिशा"],
    "filePath": "media/✽104.01 Samaik Path सामायीक प्रतिज्ञा चारो दिशा में Namostu corus.mp3"
  },
  {
    "id": "s005",
    "fileName": "✽106.03 Alochna Path Duel New आलोचना पाठ Nomu ParasTV MF sup.mp3",
    "displayName": "आलोचना पाठ — Duel New (ParasTV)",
    "alternateNames": ["alochna", "आलोचना", "duel", "parastv", "nomu", "path"],
    "filePath": "media/✽106.03 Alochna Path Duel New आलोचना पाठ Nomu ParasTV MF sup.mp3"
  },
  {
    "id": "s006",
    "fileName": "❀106.01 Alochna Path Duel New आलोचना पाठ Duel M NEW 1.mp3",
    "displayName": "आलोचना पाठ — Duel M New 1",
    "alternateNames": ["alochna", "आलोचना", "duel", "path", "new"],
    "filePath": "media/❀106.01 Alochna Path Duel New आलोचना पाठ Duel M NEW 1.mp3"
  }
]
